docs/__init__.py
docs/conf.py
docs/docs_settings.py
fiber/__init__.py
fiber/admin.py
fiber/admin_forms.py
fiber/admin_urls.py
fiber/admin_views.py
fiber/app_settings.py
fiber/apps.py
fiber/editor.py
fiber/managers.py
fiber/middleware.py
fiber/mixins.py
fiber/models.py
fiber/permissions.py
fiber/sitemaps.py
fiber/views.py
fiber/editor_definitions/__init__.py
fiber/editor_definitions/ckeditor.py
fiber/editor_definitions/markitup.py
fiber/fiber_admin/__init__.py
fiber/fiber_admin/options.py
fiber/locale/en/LC_MESSAGES/django.mo
fiber/locale/en/LC_MESSAGES/django.po
fiber/locale/en/LC_MESSAGES/djangojs.mo
fiber/locale/en/LC_MESSAGES/djangojs.po
fiber/locale/es_ES/LC_MESSAGES/django.mo
fiber/locale/es_ES/LC_MESSAGES/django.po
fiber/locale/es_ES/LC_MESSAGES/djangojs.mo
fiber/locale/es_ES/LC_MESSAGES/djangojs.po
fiber/locale/nb_NO/LC_MESSAGES/django.mo
fiber/locale/nb_NO/LC_MESSAGES/django.po
fiber/locale/nb_NO/LC_MESSAGES/djangojs.mo
fiber/locale/nb_NO/LC_MESSAGES/djangojs.po
fiber/locale/nl/LC_MESSAGES/django.mo
fiber/locale/nl/LC_MESSAGES/django.po
fiber/locale/nl/LC_MESSAGES/djangojs.mo
fiber/locale/nl/LC_MESSAGES/djangojs.po
fiber/locale/nn_NO/LC_MESSAGES/django.mo
fiber/locale/nn_NO/LC_MESSAGES/django.po
fiber/locale/nn_NO/LC_MESSAGES/djangojs.mo
fiber/locale/nn_NO/LC_MESSAGES/djangojs.po
fiber/locale/no/LC_MESSAGES/django.mo
fiber/locale/no/LC_MESSAGES/django.po
fiber/locale/no/LC_MESSAGES/djangojs.mo
fiber/locale/no/LC_MESSAGES/djangojs.po
fiber/locale/pt_BR/LC_MESSAGES/django.mo
fiber/locale/pt_BR/LC_MESSAGES/django.po
fiber/locale/pt_BR/LC_MESSAGES/djangojs.mo
fiber/locale/pt_BR/LC_MESSAGES/djangojs.po
fiber/locale/ru/LC_MESSAGES/django.mo
fiber/locale/ru/LC_MESSAGES/django.po
fiber/locale/ru/LC_MESSAGES/djangojs.mo
fiber/locale/ru/LC_MESSAGES/djangojs.po
fiber/migrations/0001_initial.py
fiber/migrations/0002_callable_upload_to.py
fiber/migrations/0003_update_mptt_fields.py
fiber/migrations/__init__.py
fiber/rest_api/__init__.py
fiber/rest_api/fields.py
django_fiber-1.10.dist-info/LICENSE.rst
django_fiber-1.10.dist-info/METADATA
django_fiber-1.10.dist-info/WHEEL
django_fiber-1.10.dist-info/top_level.txt
django_fiber-1.10.dist-info/RECORD
