Metadata-Version: 2.1
Name: django-fiber
Version: 1.10
Summary: Django Fiber - a simple, user-friendly CMS for all your Django projects
Home-page: https://github.com/django-fiber/django-fiber
Author: Dennis Bunskoek
Author-email: dbunskoek@leukeleu.nl
License: Apache License, Version 2.0
Keywords: cms,django
Platform: UNKNOWN
Classifier: Development Status :: 5 - Production/Stable
Classifier: Environment :: Web Environment
Classifier: Intended Audience :: Developers
Classifier: License :: OSI Approved :: Apache Software License
Classifier: Operating System :: OS Independent
Classifier: Programming Language :: Python :: 3
Classifier: Programming Language :: Python :: 3 :: Only
Classifier: Programming Language :: Python :: 3.6
Classifier: Programming Language :: Python :: 3.7
Classifier: Programming Language :: Python :: 3.8
Classifier: Programming Language :: Python :: 3.9
Classifier: Programming Language :: Python :: 3.10
Classifier: Framework :: Django
Classifier: Framework :: Django :: 3.2
Classifier: Framework :: Django :: 4.0
Classifier: Framework :: Django :: 4.1
Requires-Python: >=3.6
Requires-Dist: django-mptt (>=0.13)
Requires-Dist: django-compressor (>=4.1)
Requires-Dist: djangorestframework (>=3.14)
Requires-Dist: easy-thumbnails (>=2.7.2)
